tvsort_sl/__init__.py
tvsort_sl/app.py
tvsort_sl/conf.py
tvsort_sl/messages.py
tvsort_sl/utils.py
tvsort_sl-1.1.13.dist-info/LICENSE.txt
tvsort_sl-1.1.13.dist-info/METADATA
tvsort_sl-1.1.13.dist-info/WHEEL
tvsort_sl-1.1.13.dist-info/top_level.txt
tvsort_sl-1.1.13.dist-info/RECORD
