Metadata-Version: 2.1
Name: tvsort-sl
Version: 1.1.13
Summary: Sort movies and TV-shows files
Home-page: https://github.com/shlomiLan/tvsort_sl
Author: Shlomi Lanton
Author-email: shlomilanton@gmail.com
License: UNKNOWN
Download-URL: https://github.com/shlomiLan/tvsort_sl/archive/0.1.zip
Keywords: sort,tv,show,movie,KODI,XBM1C
Platform: UNKNOWN
